pygeochemtools/__init__.py
pygeochemtools/_version.py
pygeochemtools/cli.py
pygeochemtools/data/__init__.py
pygeochemtools/data/sarig_method_code_map.csv
pygeochemtools/data/user_config.yml
pygeochemtools/geochem/__init__.py
pygeochemtools/geochem/aggregation.py
pygeochemtools/geochem/conversions.py
pygeochemtools/geochem/create_dataset.py
pygeochemtools/geochem/normalisation.py
pygeochemtools/geochem/transform.py
pygeochemtools/map/__init__.py
pygeochemtools/map/interpolate.py
pygeochemtools/map/map.py
pygeochemtools/utils/__init__.py
pygeochemtools/utils/app_logger.py
pygeochemtools/utils/config.py
pygeochemtools/utils/export.py
pygeochemtools-0.1.2.dist-info/LICENSE
pygeochemtools-0.1.2.dist-info/METADATA
pygeochemtools-0.1.2.dist-info/WHEEL
pygeochemtools-0.1.2.dist-info/entry_points.txt
pygeochemtools-0.1.2.dist-info/top_level.txt
pygeochemtools-0.1.2.dist-info/RECORD
