Metadata-Version: 2.1
Name: pygeochemtools
Version: 0.1.2
Summary: An eclectic set of geochemical data manipulation, QC and plotting tools.
Home-page: https://github.com/RADutchie/pygeochemtools
Author: Rian Dutch
Author-email: riandutch@gmail.com
License: MIT
Project-URL: Documentation, https://pygeochemtools.readthedocs.io/en/latest/
Project-URL: Blog, https://geodataanalytics.net/
Keywords: geology,earth science,geoscience,exploration,geochemistry
Platform: UNKNOWN
Classifier: Development Status :: 3 - Alpha
Classifier: Intended Audience :: Science/Research
Classifier: Topic :: Scientific/Engineering
Classifier: License :: OSI Approved :: MIT License
Classifier: Programming Language :: Python :: 3.8
Classifier: Operating System :: OS Independent
Requires-Python: >=3.8
License-File: LICENSE
Requires-Dist: click (>=8)
Requires-Dist: numpy (>=1.20)
Requires-Dist: pandas (>=1.2)
Requires-Dist: dask (>=2021.6)
Requires-Dist: matplotlib (>=3.3)
Requires-Dist: metpy (>=1.0)
Requires-Dist: PyYAML (>=5.0)
Requires-Dist: rich (>=10.13)
Provides-Extra: cartopy
Requires-Dist: Cartopy (>=0.19.0.post1) ; extra == 'cartopy'
